sudosu/__init__.py
sudosu/cli.py
sudosu/commands/__init__.py
sudosu/commands/agent.py
sudosu/commands/config.py
sudosu/commands/init.py
sudosu/commands/integrations.py
sudosu/commands/memory.py
sudosu/commands/onboarding.py
sudosu/commands/tasks.py
sudosu/core/__init__.py
sudosu/core/agent_loader.py
sudosu/core/api_client.py
sudosu/core/connection.py
sudosu/core/default_agent.py
sudosu/core/prompt_refiner.py
sudosu/core/safety.py
sudosu/core/session.py
sudosu/core/task_storage.py
sudosu/tools/__init__.py
sudosu/ui/__init__.py
sudosu-0.1.7.dist-info/licenses/LICENSE
sudosu-0.1.7.dist-info/METADATA
sudosu-0.1.7.dist-info/WHEEL
sudosu-0.1.7.dist-info/entry_points.txt
sudosu-0.1.7.dist-info/top_level.txt
sudosu-0.1.7.dist-info/RECORD
