Metadata-Version: 2.4
Name: sudosu
Version: 0.1.7
Summary: Your AI Coworker - that can actually get work done. Unlike chatbots that just talk, these teammates can read your files, write code, create documents, connect to all your tools (Gmail, Calendar, GitHub, Linear, Slack), and run commands - all while you stay in control
Author: Akash Munshi
License-Expression: MIT
Project-URL: Homepage, https://github.com/csakash/sudosu-cli
Project-URL: Repository, https://github.com/csakash/sudosu-cli
Project-URL: Issues, https://github.com/csakash/sudosu-cli/issues
Keywords: ai,assistant,cli,automation,agent,coworker,productivity,llm
Classifier: Development Status :: 3 - Alpha
Classifier: Environment :: Console
Classifier: Intended Audience :: Developers
Classifier: Programming Language :: Python :: 3
Classifier: Programming Language :: Python :: 3.10
Classifier: Programming Language :: Python :: 3.11
Classifier: Programming Language :: Python :: 3.12
Classifier: Topic :: Software Development :: Libraries :: Python Modules
Classifier: Topic :: Office/Business
Classifier: Topic :: Communications
Requires-Python: >=3.10
License-File: LICENSE
Requires-Dist: typer>=0.9.0
Requires-Dist: rich>=13.0.0
Requires-Dist: websockets>=12.0
Requires-Dist: pyyaml>=6.0
Requires-Dist: python-frontmatter>=1.0.0
Requires-Dist: httpx>=0.25.0
Requires-Dist: prompt-toolkit>=3.0.0
Requires-Dist: python-dotenv>=1.0.0
Requires-Dist: certifi>=2023.0.0
Provides-Extra: dev
Requires-Dist: pytest>=7.0.0; extra == "dev"
Requires-Dist: pytest-asyncio>=0.21.0; extra == "dev"
Requires-Dist: black>=23.0.0; extra == "dev"
Requires-Dist: ruff>=0.1.0; extra == "dev"
Dynamic: license-file
